aio_zmq_rpc/__init__.py
aio_zmq_rpc-0.7.dist-info/WHEEL
aio_zmq_rpc-0.7.dist-info/METADATA
aio_zmq_rpc-0.7.dist-info/RECORD
