Metadata-Version: 2.1
Name: aio-zmq-rpc
Version: 0.7
Summary: 
Author: Alexander Titoff
Author-email: a.tit.off@gmail.com
Requires-Python: >=3.7,<4.0
Classifier: Programming Language :: Python :: 3
Classifier: Programming Language :: Python :: 3.7
Classifier: Programming Language :: Python :: 3.8
Requires-Dist: msgpack (>=1.0.0,<2.0.0)
Requires-Dist: pyzmq (>=19.0.0,<20.0.0)
Project-URL: Documentation, https://github.com/atitoff/aio_zmq_rpc
